LICENSE
MANIFEST.in
README.md
demo.py
setup.py
visualization.py
auto_crop.egg-info/PKG-INFO
auto_crop.egg-info/SOURCES.txt
auto_crop.egg-info/dependency_links.txt
auto_crop.egg-info/requires.txt
auto_crop.egg-info/top_level.txt
autocrop/__init__.py
autocrop/cropper.py
autocrop/utils.py
autocrop/model/__init__.py
autocrop/model/cropping_model.py
autocrop/model/moblienetv2.py
autocrop/model/shufflenetv2.py
autocrop/model/rod_align/__init__.py
autocrop/model/rod_align/setup.py
autocrop/model/rod_align/functions/__init__.py
autocrop/model/rod_align/functions/rod_align.py
autocrop/model/rod_align/modules/__init__.py
autocrop/model/rod_align/modules/rod_align.py
autocrop/model/rod_align/src/rod_align.cpp
autocrop/model/rod_align/src/rod_align.h
autocrop/model/rod_align/src/rod_align_cuda.cpp
autocrop/model/rod_align/src/rod_align_cuda.h
autocrop/model/rod_align/src/rod_align_kernel.cu
autocrop/model/rod_align/src/rod_align_kernel.h
autocrop/model/roi_align/__init__.py
autocrop/model/roi_align/setup.py
autocrop/model/roi_align/functions/__init__.py
autocrop/model/roi_align/functions/roi_align.py
autocrop/model/roi_align/modules/__init__.py
autocrop/model/roi_align/modules/roi_align.py
autocrop/model/roi_align/src/roi_align.cpp
autocrop/model/roi_align/src/roi_align.h
autocrop/model/roi_align/src/roi_align_cuda.cpp
autocrop/model/roi_align/src/roi_align_cuda.h
autocrop/model/roi_align/src/roi_align_kernel.cu
autocrop/model/roi_align/src/roi_align_kernel.h
imgs/.DS_Store
imgs/demo.jpg
imgs/test.jpg
imgs/test2.jpg
misc/.DS_Store
misc/1x1_ret_F.jpg
misc/1x1_ret_NF.jpg
misc/2x5_ret_F.jpg
misc/2x5_ret_NF.jpg
misc/Pipeline.png
misc/face_filter.jpg
misc/face_filter2.jpg