Metadata-Version: 2.1
Name: auto-crop
Version: 0.3.0
Summary: Smart auto cropping tool that supports any aspect ratio
Home-page: https://github.com/lih627/autocrop
Author: Hao Li
Author-email: lih627@outlook.com
License: MIT
Platform: UNKNOWN
Classifier: Development Status :: 5 - Production/Stable
Classifier: License :: OSI Approved :: MIT License
Classifier: Operating System :: OS Independent
Requires-Python: >=3.5
